centurymetadata/__init__.py
centurymetadata/constants.py
centurymetadata/decode.py
centurymetadata/encode.py
centurymetadata/server/server.py
centurymetadata/server/setup.sh
centurymetadata-0.2.dist-info/WHEEL
centurymetadata-0.2.dist-info/METADATA
centurymetadata-0.2.dist-info/RECORD
