Metadata-Version: 2.1
Name: centurymetadata
Version: 0.2
Summary: Encrypt, send, retrieve and decrypt centurymetadata.org files
Home-page: https://centurymetadata.org/
License: MIT
Author: Rusty Russell
Author-email: rusty@rustcorp.com.au
Requires-Python: >=3.8
Classifier: License :: OSI Approved :: MIT License
Classifier: Programming Language :: Python :: 3
Classifier: Programming Language :: Python :: 3.10
Classifier: Programming Language :: Python :: 3.8
Classifier: Programming Language :: Python :: 3.9
Requires-Dist: pycryptodomex (>=3.6)
Requires-Dist: secp256k1 (>=0.14.0)
Project-URL: Repository, https://github.com/rustyrussell/centurymetadata/
